.gitignore
LICENSE
MANIFEST.in
README.rst
setup.py
django_json_settings.egg-info/PKG-INFO
django_json_settings.egg-info/SOURCES.txt
django_json_settings.egg-info/dependency_links.txt
django_json_settings.egg-info/top_level.txt
json_settings/__init__.py