Metadata-Version: 1.0
Name: django-json-settings
Version: 0.2
Summary: A Django application to let you provide local settings in json format
Home-page: http://github.com/isotoma/django-json-settings
Author: Doug Winter
Author-email: doug.winter@isotoma.com
License: Apache Software License
Platform: UNKNOWN
